gpt/__init__.py
gpt/openai.py
gpt/sdk.py
gpt/models/__init__.py
gpt/models/operations/__init__.py
gpt/models/operations/cancelfinetune.py
gpt/models/operations/createanswer.py
gpt/models/operations/createchatcompletion.py
gpt/models/operations/createclassification.py
gpt/models/operations/createcompletion.py
gpt/models/operations/createedit.py
gpt/models/operations/createembedding.py
gpt/models/operations/createfile.py
gpt/models/operations/createfinetune.py
gpt/models/operations/createimage.py
gpt/models/operations/createimageedit.py
gpt/models/operations/createimagevariation.py
gpt/models/operations/createmoderation.py
gpt/models/operations/createsearch.py
gpt/models/operations/createtranscription.py
gpt/models/operations/createtranslation.py
gpt/models/operations/deletefile.py
gpt/models/operations/deletemodel.py
gpt/models/operations/downloadfile.py
gpt/models/operations/listengines.py
gpt/models/operations/listfiles.py
gpt/models/operations/listfinetuneevents.py
gpt/models/operations/listfinetunes.py
gpt/models/operations/listmodels.py
gpt/models/operations/retrieveengine.py
gpt/models/operations/retrievefile.py
gpt/models/operations/retrievefinetune.py
gpt/models/operations/retrievemodel.py
gpt/models/shared/__init__.py
gpt/models/shared/chatcompletionrequestmessage.py
gpt/models/shared/chatcompletionresponsemessage.py
gpt/models/shared/createanswerrequest.py
gpt/models/shared/createanswerresponse.py
gpt/models/shared/createchatcompletionrequest.py
gpt/models/shared/createchatcompletionresponse.py
gpt/models/shared/createclassificationrequest.py
gpt/models/shared/createclassificationresponse.py
gpt/models/shared/createcompletionrequest.py
gpt/models/shared/createcompletionresponse.py
gpt/models/shared/createeditrequest.py
gpt/models/shared/createeditresponse.py
gpt/models/shared/createembeddingrequest.py
gpt/models/shared/createembeddingresponse.py
gpt/models/shared/createfilerequest.py
gpt/models/shared/createfinetunerequest.py
speakeasy_openai-1.3.0.dist-info/LICENSE
speakeasy_openai-1.3.0.dist-info/METADATA
speakeasy_openai-1.3.0.dist-info/WHEEL
speakeasy_openai-1.3.0.dist-info/top_level.txt
speakeasy_openai-1.3.0.dist-info/RECORD
